{
    "policies": [
        {
            "id": "pol_us_ind_payout_2024_1",
            "version": "2024.1-US-INDIVIDUAL",
            "countryCode": "US",
            "sellerType": "INDIVIDUAL",
            "status": "ACTIVE",
            "effectiveFrom": "2024-01-01",
            "effectiveTo": null,
            "deprecatedDate": null,
            "createdBy": "system",
            "createdAt": "2024-01-01T00:00:00",
            "approvedBy": "compliance-officer",
            "approvedAt": "2024-01-01T00:00:00",
            "description": "Standard US individual seller payout policy",
            "regulatoryBasis": "US banking regulations, ACH transfer requirements, IRS 1099-K reporting",
            "defaultFrequency": "WEEKLY",
            "minimumThreshold": 25.00,
            "currency": "USD",
            "holdPeriodDays": 7,
            "rollingReservePercentage": 10.00,
            "reserveReleaseDays": 90,
            "rules": [
                {
                    "id": "rule_us_ind_standard",
                    "ruleName": "standard_payout",
                    "ruleOrder": 1,
                    "frequency": "WEEKLY",
                    "threshold": 25.00,
                    "holdPeriodDays": 7,
                    "eligibilityCriteria": {},
                    "ruleConfig": {
                        "payout_day": "FRIDAY",
                        "method": "ACH",
                        "description": "Standard weekly ACH payout"
                    }
                },
                {
                    "id": "rule_us_ind_accelerated",
                    "ruleName": "accelerated_payout",
                    "ruleOrder": 2,
                    "frequency": "DAILY",
                    "threshold": 100.00,
                    "holdPeriodDays": 2,
                    "eligibilityCriteria": {
                        "min_sales_count": 50,
                        "account_age_days": 90,
                        "min_rating": 4.5
                    },
                    "ruleConfig": {
                        "method": "INSTANT",
                        "fee_percentage": 1.5,
                        "description": "Instant daily payout for qualified sellers"
                    }
                }
            ]
        },
        {
            "id": "pol_in_ind_payout_2024_1",
            "version": "2024.1-IN-INDIVIDUAL",
            "countryCode": "IN",
            "sellerType": "INDIVIDUAL",
            "status": "ACTIVE",
            "effectiveFrom": "2024-01-01",
            "effectiveTo": null,
            "deprecatedDate": null,
            "createdBy": "system",
            "createdAt": "2024-01-01T00:00:00",
            "approvedBy": "compliance-officer",
            "approvedAt": "2024-01-01T00:00:00",
            "description": "Standard India individual seller payout policy",
            "regulatoryBasis": "RBI guidelines, NEFT/RTGS regulations, GST compliance, Income Tax Act",
            "defaultFrequency": "BIWEEKLY",
            "minimumThreshold": 500.00,
            "currency": "INR",
            "holdPeriodDays": 14,
            "rollingReservePercentage": 15.00,
            "reserveReleaseDays": 120,
            "rules": [
                {
                    "id": "rule_in_ind_standard",
                    "ruleName": "standard_payout",
                    "ruleOrder": 1,
                    "frequency": "BIWEEKLY",
                    "threshold": 500.00,
                    "holdPeriodDays": 14,
                    "eligibilityCriteria": {},
                    "ruleConfig": {
                        "payout_days": [
                            "1st",
                            "15th"
                        ],
                        "method": "NEFT",
                        "description": "Bi-weekly NEFT payout"
                    }
                },
                {
                    "id": "rule_in_ind_weekly",
                    "ruleName": "weekly_payout",
                    "ruleOrder": 2,
                    "frequency": "WEEKLY",
                    "threshold": 2000.00,
                    "holdPeriodDays": 7,
                    "eligibilityCriteria": {
                        "min_sales_count": 100,
                        "account_age_days": 180,
                        "gst_verified": true
                    },
                    "ruleConfig": {
                        "payout_day": "MONDAY",
                        "method": "RTGS",
                        "description": "Weekly RTGS payout for GST-verified sellers"
                    }
                }
            ]
        },
        {
            "id": "pol_de_bus_payout_2024_1",
            "version": "2024.1-DE-BUSINESS",
            "countryCode": "DE",
            "sellerType": "BUSINESS",
            "status": "ACTIVE",
            "effectiveFrom": "2024-01-01",
            "effectiveTo": null,
            "deprecatedDate": null,
            "createdBy": "system",
            "createdAt": "2024-01-01T00:00:00",
            "approvedBy": "compliance-officer",
            "approvedAt": "2024-01-01T00:00:00",
            "description": "Standard Germany business seller payout policy",
            "regulatoryBasis": "SEPA regulations, EU Payment Services Directive (PSD2), VAT compliance, German Commercial Code",
            "defaultFrequency": "MONTHLY",
            "minimumThreshold": 50.00,
            "currency": "EUR",
            "holdPeriodDays": 10,
            "rollingReservePercentage": 5.00,
            "reserveReleaseDays": 60,
            "rules": [
                {
                    "id": "rule_de_bus_standard",
                    "ruleName": "standard_payout",
                    "ruleOrder": 1,
                    "frequency": "MONTHLY",
                    "threshold": 50.00,
                    "holdPeriodDays": 10,
                    "eligibilityCriteria": {},
                    "ruleConfig": {
                        "payout_day": "LAST_DAY_OF_MONTH",
                        "method": "SEPA",
                        "description": "Monthly SEPA payout"
                    }
                },
                {
                    "id": "rule_de_bus_weekly",
                    "ruleName": "weekly_payout",
                    "ruleOrder": 2,
                    "frequency": "WEEKLY",
                    "threshold": 500.00,
                    "holdPeriodDays": 5,
                    "eligibilityCriteria": {
                        "min_sales_count": 200,
                        "account_age_days": 365,
                        "vat_verified": true
                    },
                    "ruleConfig": {
                        "payout_day": "FRIDAY",
                        "method": "SEPA_INSTANT",
                        "description": "Weekly SEPA Instant payout for VAT-verified businesses"
                    }
                }
            ]
        }
    ]
}